{"is_source_file": true, "format": "HTML", "description": "This is an HTML file that serves as the entry point for a web application, providing the basic structure for the application layout, referencing stylesheets, and setting metadata.", "external_files": ["%PUBLIC_URL%/favicon.ico", "%PUBLIC_URL%/logo192.png", "%PUBLIC_URL%/manifest.json", "https://fonts.googleapis.com/css2?family=Inter:wght@400;500;600;700&display=swap"], "external_methods": [], "published": [], "classes": [], "methods": [], "calls": [], "search-terms": ["index", "html", "kavia", "app", "todo"], "state": 2, "file_id": 9, "knowledge_revision": 25, "git_revision": "b0d831a8d4f41b4a488a998e54ce8016ea51c018", "hash": "d2b40d02d5f7873d8a6713bad837edd4", "format-version": 4, "code-base-name": "todo_frontend", "filename": "todo_frontend/public/index.html", "revision_history": [{"25": "b0d831a8d4f41b4a488a998e54ce8016ea51c018"}]}